feedback_image_trainer/__init__.py
feedback_image_trainer/dataset.py
feedback_image_trainer/main.py
feedback_image_trainer/trainer.py
feedback_image_trainer-0.1.0.dist-info/METADATA
feedback_image_trainer-0.1.0.dist-info/WHEEL
feedback_image_trainer-0.1.0.dist-info/top_level.txt
feedback_image_trainer-0.1.0.dist-info/RECORD
