Metadata-Version: 2.4
Name: feedback_image_trainer
Version: 0.1.0
Summary: Fine-tune Stable Diffusion with feedback-driven Optuna hyperparameter search
Author: Your Name
Author-email: your.email@example.com
License: MIT
Classifier: Programming Language :: Python :: 3
Classifier: License :: OSI Approved :: MIT License
Classifier: Operating System :: OS Independent
Requires-Python: >=3.8
Requires-Dist: torch>=2.0.0
Requires-Dist: diffusers>=0.20.0
Requires-Dist: transformers>=4.30.0
Requires-Dist: accelerate>=0.20.0
Requires-Dist: optuna>=2.0.0
Requires-Dist: torchvision>=0.15.0
Dynamic: author
Dynamic: author-email
Dynamic: classifier
Dynamic: description
Dynamic: description-content-type
Dynamic: license
Dynamic: requires-dist
Dynamic: requires-python
Dynamic: summary
